min_tfs_client/constants.py
min_tfs_client/requests.py
min_tfs_client/tensors.py
min_tfs_client/types.py
tensorflow/compiler/jit/xla_activity_pb2.py
tensorflow/compiler/mlir/lite/quantization/quantization_info_pb2.py
tensorflow/compiler/tf2tensorrt/utils/trt_engine_instance_pb2.py
tensorflow/compiler/tf2xla/host_compute_metadata_pb2.py
tensorflow/compiler/tf2xla/tf2xla_pb2.py
tensorflow/compiler/xla/xla_data_pb2.py
tensorflow/compiler/xla/xla_pb2.py
tensorflow/compiler/xla/python/tpu_driver/tpu_driver_pb2.py
tensorflow/compiler/xla/python/tpu_driver/tpu_service_pb2.py
tensorflow/compiler/xla/rpc/xla_service_pb2.py
tensorflow/compiler/xla/service/hlo_execution_profile_data_pb2.py
tensorflow/compiler/xla/service/hlo_pb2.py
tensorflow/compiler/xla/service/hlo_profile_printer_data_pb2.py
tensorflow/compiler/xla/service/gpu/backend_configs_pb2.py
tensorflow/compiler/xla/service/gpu/gpu_autotuning_pb2.py
tensorflow/compiler/xrt/xrt_pb2.py
tensorflow/core/debug/debug_service_pb2.py
tensorflow/core/debug/debugger_event_metadata_pb2.py
tensorflow/core/example/example_parser_configuration_pb2.py
tensorflow/core/example/example_pb2.py
tensorflow/core/example/feature_pb2.py
tensorflow/core/framework/allocation_description_pb2.py
tensorflow/core/framework/api_def_pb2.py
tensorflow/core/framework/attr_value_pb2.py
tensorflow/core/framework/cost_graph_pb2.py
tensorflow/core/framework/device_attributes_pb2.py
tensorflow/core/framework/function_pb2.py
tensorflow/core/framework/graph_pb2.py
tensorflow/core/framework/graph_transfer_info_pb2.py
tensorflow/core/framework/kernel_def_pb2.py
tensorflow/core/framework/log_memory_pb2.py
tensorflow/core/framework/node_def_pb2.py
tensorflow/core/framework/op_def_pb2.py
tensorflow/core/framework/reader_base_pb2.py
tensorflow/core/framework/remote_fused_graph_execute_info_pb2.py
tensorflow/core/framework/resource_handle_pb2.py
tensorflow/core/framework/step_stats_pb2.py
tensorflow/core/framework/summary_pb2.py
min_tfs_client-1.0.2.dist-info/LICENCE
min_tfs_client-1.0.2.dist-info/METADATA
min_tfs_client-1.0.2.dist-info/WHEEL
min_tfs_client-1.0.2.dist-info/top_level.txt
min_tfs_client-1.0.2.dist-info/RECORD
