Metadata-Version: 2.1
Name: min-tfs-client
Version: 1.0.2
Summary: A minified Tensor Serving Client for Python
Home-page: UNKNOWN
License: UNKNOWN
Platform: UNKNOWN
Requires-Dist: grpcio (>=1.21)
Requires-Dist: protobuf (>=3.8)
Requires-Dist: numpy (>=1.16.4)
Provides-Extra: dev
Requires-Dist: black (==19.10b0) ; extra == 'dev'
Requires-Dist: flake8 ; extra == 'dev'
Requires-Dist: mypy ; extra == 'dev'
